IndicLatinSoundex/__init__.py
IndicLatinSoundex/main.py
IndicLatinSoundex-0.2.dist-info/METADATA
IndicLatinSoundex-0.2.dist-info/WHEEL
IndicLatinSoundex-0.2.dist-info/top_level.txt
IndicLatinSoundex-0.2.dist-info/RECORD
