Metadata-Version: 2.1
Name: IndicLatinSoundex
Version: 0.2
Summary: UNKNOWN
Home-page: UNKNOWN
License: UNKNOWN
Platform: UNKNOWN
